{
  "account": "linh",
  "skill": "multi_skill",
  "final_result": "html:UNSUPPORTED_SENIORITY | css:UNSUPPORTED_SENIORITY | javascript:UNSUPPORTED_SENIORITY | react:UNSUPPORTED_SENIORITY | github:UNSUPPORTED_SENIORITY",
  "failed": false,
  "history": {
    "account": "linh",
    "results": [
      {
        "skill": "html",
        "final_result": "UNSUPPORTED_SENIORITY",
        "failed": true,
        "answer_history": [
          {
            "question_id": "137",
            "selected_index": 1,
            "is_correct": false
          }
        ]
      },
      {
        "skill": "css",
        "final_result": "UNSUPPORTED_SENIORITY",
        "failed": true,
        "answer_history": [
          {
            "question_id": "238",
            "selected_index": 2,
            "is_correct": false
          }
        ]
      },
      {
        "skill": "javascript",
        "final_result": "UNSUPPORTED_SENIORITY",
        "failed": true,
        "answer_history": [
          {
            "question_id": "337",
            "selected_index": 1,
            "is_correct": false
          }
        ]
      },
      {
        "skill": "react",
        "final_result": "UNSUPPORTED_SENIORITY",
        "failed": true,
        "answer_history": [
          {
            "question_id": "37",
            "selected_index": 2,
            "is_correct": false
          }
        ]
      },
      {
        "skill": "github",
        "final_result": "UNSUPPORTED_SENIORITY",
        "failed": true,
        "answer_history": [
          {
            "question_id": "439",
            "selected_index": 2,
            "is_correct": false
          }
        ]
      }
    ],
    "summary": {
      "html": "UNSUPPORTED_SENIORITY",
      "css": "UNSUPPORTED_SENIORITY",
      "javascript": "UNSUPPORTED_SENIORITY",
      "react": "UNSUPPORTED_SENIORITY",
      "github": "UNSUPPORTED_SENIORITY"
    },
    "timestamp": "2025-07-09T06:48:43.303876"
  },
  "timestamp": "2025-07-09T13:48:43.305429+07:00"
}